{
  "schemaVersion": "6.1.0",
  "build": {
    "version": "6.1.0-production-user-testing",
    "milestone": "Production User Testing Release",
    "status": "healthy",
    "buildTime": "2026-07-22T00:09:57.576Z",
    "note": "All connected data sources are healthy.",
    "alerts": 0,
    "incidents": 0,
    "weatherRegions": 5,
    "riverEvents": 13,
    "journeys": 3,
    "officialSourcesConfigured": 7,
    "trustedMediaSourcesConfigured": 28,
    "sourceSummary": {
      "total": 11,
      "healthy": 11,
      "stale": 0,
      "unavailable": 0,
      "unverified": 0
    }
  }
}