{
  "schemaVersion": "6.1.0",
  "generatedAt": "2026-07-11T01:09:57.890Z",
  "weatherSource": {
    "status": "current",
    "sourceCheckedAt": "2026-07-11T01:09:57.267Z",
    "lastSuccessfulAt": "2026-07-11T01:09:57.267Z",
    "staleAfterMinutes": 60,
    "attribution": {
      "name": "Open-Meteo",
      "url": "https://open-meteo.com/"
    },
    "error": null
  },
  "riverSource": {
    "status": "unavailable",
    "sourceCheckedAt": null,
    "lastSuccessfulAt": null,
    "error": "No live river or dam collector is connected."
  },
  "weatherIntelligence": {
    "generatedAt": "2026-07-11T01:09:57.888Z",
    "regions": {
      "pune_city": {
        "label": "Pune City",
        "latitude": 18.523726,
        "longitude": 73.86876,
        "source": "Open-Meteo",
        "sourceUrl": "https://open-meteo.com/",
        "sourceCheckedAt": "2026-07-11T01:09:57.267Z",
        "observedAt": "2026-07-11T06:30:00+05:30",
        "temp": 23.5,
        "rain6h": 0,
        "precipitationProbability": 5,
        "wind": 37.1,
        "gust": 37.1,
        "humidity": 90,
        "visibility": 17.1,
        "weatherCode": 3,
        "rainRisk": "Minimal",
        "windRisk": "Low",
        "visibilityRisk": "Minimal",
        "heatRisk": "Normal",
        "travelImpact": "Low",
        "advice": [
          "No major weather-related disruption indicated."
        ]
      },
      "pcmc": {
        "label": "Pimpri-Chinchwad",
        "latitude": 18.594023,
        "longitude": 73.76471,
        "source": "Open-Meteo",
        "sourceUrl": "https://open-meteo.com/",
        "sourceCheckedAt": "2026-07-11T01:09:57.267Z",
        "observedAt": "2026-07-11T06:30:00+05:30",
        "temp": 23.5,
        "rain6h": 0,
        "precipitationProbability": 7,
        "wind": 29.9,
        "gust": 29.9,
        "humidity": 91,
        "visibility": 13.5,
        "weatherCode": 3,
        "rainRisk": "Minimal",
        "windRisk": "Low",
        "visibilityRisk": "Minimal",
        "heatRisk": "Normal",
        "travelImpact": "Low",
        "advice": [
          "No major weather-related disruption indicated."
        ]
      },
      "pune_district": {
        "label": "Pune District",
        "latitude": 18.523726,
        "longitude": 73.86876,
        "source": "Open-Meteo",
        "sourceUrl": "https://open-meteo.com/",
        "sourceCheckedAt": "2026-07-11T01:09:57.267Z",
        "observedAt": "2026-07-11T06:30:00+05:30",
        "temp": 23.5,
        "rain6h": 0,
        "precipitationProbability": 5,
        "wind": 37.1,
        "gust": 37.1,
        "humidity": 90,
        "visibility": 17.1,
        "weatherCode": 3,
        "rainRisk": "Minimal",
        "windRisk": "Low",
        "visibilityRisk": "Minimal",
        "heatRisk": "Normal",
        "travelImpact": "Low",
        "advice": [
          "No major weather-related disruption indicated."
        ]
      },
      "mulshi": {
        "label": "Mulshi",
        "latitude": 18.523726,
        "longitude": 73.51617,
        "source": "Open-Meteo",
        "sourceUrl": "https://open-meteo.com/",
        "sourceCheckedAt": "2026-07-11T01:09:57.267Z",
        "observedAt": "2026-07-11T06:30:00+05:30",
        "temp": 22.8,
        "rain6h": 2,
        "precipitationProbability": 100,
        "wind": 43.2,
        "gust": 43.2,
        "humidity": 99,
        "visibility": 0.3,
        "weatherCode": 51,
        "rainRisk": "Minimal",
        "windRisk": "Medium",
        "visibilityRisk": "High",
        "heatRisk": "Normal",
        "travelImpact": "High",
        "advice": [
          "Low visibility may make driving unsafe."
        ]
      },
      "maval": {
        "label": "Maval / Lonavala",
        "latitude": 18.80492,
        "longitude": 73.451324,
        "source": "Open-Meteo",
        "sourceUrl": "https://open-meteo.com/",
        "sourceCheckedAt": "2026-07-11T01:09:57.267Z",
        "observedAt": "2026-07-11T06:30:00+05:30",
        "temp": 22.6,
        "rain6h": 2.1,
        "precipitationProbability": 100,
        "wind": 35.6,
        "gust": 35.6,
        "humidity": 100,
        "visibility": 0.3,
        "weatherCode": 51,
        "rainRisk": "Minimal",
        "windRisk": "Low",
        "visibilityRisk": "High",
        "heatRisk": "Normal",
        "travelImpact": "High",
        "advice": [
          "Low visibility may make driving unsafe."
        ]
      }
    }
  },
  "riverIntelligence": [],
  "seasonalIntelligence": {
    "generatedAt": "2026-07-11T01:09:57.889Z",
    "activeSeason": "monsoon",
    "priorityHazards": [
      "flood",
      "dam_release",
      "waterlogging",
      "lightning",
      "landslide",
      "tree_fall"
    ],
    "advice": "Monitor rainfall, dam releases, waterlogging and ghat conditions."
  },
  "geographicIntelligence": {
    "generatedAt": "2026-07-11T01:09:57.889Z",
    "model": "administrative-ui-operational-backend",
    "operationalZones": {
      "river_corridors": [
        "Mula River",
        "Mutha River",
        "Mula-Mutha River",
        "Indrayani River",
        "Pavana River",
        "Bhima River",
        "Nira River"
      ],
      "dam_zones": [
        "Khadakwasla",
        "Panshet",
        "Varasgaon",
        "Temghar",
        "Pawna",
        "Mulshi",
        "Bhatghar",
        "Veer"
      ],
      "highway_corridors": [
        "Mumbai-Pune Expressway",
        "NH48",
        "Pune-Nashik Highway",
        "Pune-Solapur Highway",
        "Pune-Satara Highway",
        "Pune-Ahmednagar Highway"
      ],
      "ghat_zones": [
        "Tamhini Ghat",
        "Bhor Ghat",
        "Varandha Ghat",
        "Katraj Ghat",
        "Dive Ghat",
        "Khambatki Ghat"
      ],
      "it_corridors": [
        "Hinjawadi",
        "Kharadi",
        "Magarpatta",
        "Baner",
        "Balewadi",
        "Talawade"
      ]
    },
    "infrastructure": {
      "highways": [
        "Mumbai-Pune Expressway",
        "NH48",
        "Pune-Nashik Highway",
        "Pune-Solapur Highway",
        "Pune-Satara Highway",
        "Pune-Ahmednagar Highway"
      ],
      "ghats": [
        "Tamhini Ghat",
        "Bhor Ghat",
        "Varandha Ghat",
        "Katraj Ghat",
        "Dive Ghat",
        "Khambatki Ghat"
      ],
      "emergencyServices": [
        "Hospitals",
        "Police Stations",
        "Fire Stations",
        "Disaster Management"
      ],
      "transport": [
        "Pune Railway Station",
        "Shivajinagar Station",
        "Pune Metro",
        "Pune Airport",
        "MSRTC Bus Stations"
      ]
    },
    "note": "UI remains Region → Taluka → Locality. Operational geography is used only by intelligence engines."
  },
  "criticalInfrastructure": {
    "generatedAt": "2026-07-11T01:09:57.889Z",
    "mode": "on-demand",
    "relevantDomains": [],
    "infrastructure": {
      "highways": [
        "Mumbai-Pune Expressway",
        "NH48",
        "Pune-Nashik Highway",
        "Pune-Solapur Highway",
        "Pune-Satara Highway",
        "Pune-Ahmednagar Highway"
      ],
      "ghats": [
        "Tamhini Ghat",
        "Bhor Ghat",
        "Varandha Ghat",
        "Katraj Ghat",
        "Dive Ghat",
        "Khambatki Ghat"
      ],
      "emergencyServices": [
        "Hospitals",
        "Police Stations",
        "Fire Stations",
        "Disaster Management"
      ],
      "transport": [
        "Pune Railway Station",
        "Shivajinagar Station",
        "Pune Metro",
        "Pune Airport",
        "MSRTC Bus Stations"
      ]
    }
  },
  "environmentalImpact": {
    "generatedAt": "2026-07-11T01:09:57.889Z",
    "riskLevel": "Normal",
    "impacts": [],
    "citizenSummary": "No major environmental disruption indicated from current data.",
    "seasonalContext": "monsoon"
  },
  "story": "No major environmental disruption indicated from current data."
}