{
  "schemaVersion": "6.0.0",
  "generatedAt": "2026-07-17T23:09:14.992Z",
  "routes": [],
  "risks": [
    {
      "id": "heavy-rain-official-light-to-moderate-rain-is-very-likely-to-occur-at-isolated-places-over",
      "category": "heavy_rain",
      "severity": "watch",
      "localities": [],
      "talukas": [],
      "operationalZones": [],
      "impact": "This event may affect local awareness or movement."
    },
    {
      "id": "accident-developing-3-booked-for-3-separate-road-accidents-that-left-3-dead-2026-07-17t03-",
      "category": "accident",
      "severity": "watch",
      "localities": [
        "Loni Kalbhor"
      ],
      "talukas": [
        "loni_kalbhor"
      ],
      "operationalZones": [],
      "impact": "Traffic delays are likely near the incident location."
    }
  ]
}