{
  "schemaVersion": "6.0.0",
  "generatedAt": "2026-07-15T00:07:00.772Z",
  "routes": [],
  "risks": [
    {
      "id": "accident-developing-daund-woman-s-organ-donation-gives-new-lease-of-life-to-four-patients-",
      "category": "accident",
      "severity": "watch",
      "localities": [
        "Daund"
      ],
      "talukas": [
        "daund"
      ],
      "operationalZones": [],
      "impact": "Traffic delays are likely near the incident location."
    },
    {
      "id": "accident-developing-3-women-warkaris-killed-7-injured-in-palkhi-truck-hit-2026-07-14t03-14",
      "category": "accident",
      "severity": "watch",
      "localities": [],
      "talukas": [],
      "operationalZones": [],
      "impact": "Traffic delays are likely near the incident location."
    },
    {
      "id": "flood-developing-kanda-market-लासलगाव-पिंपळगाव-पुण्यात-कांद्याचे-दर-सुधारले-सोलापूरमध्ये-म",
      "category": "flood",
      "severity": "warning",
      "localities": [],
      "talukas": [],
      "operationalZones": [],
      "impact": "This event may affect local awareness or movement."
    }
  ]
}