{
  "schemaVersion": "6.1.0",
  "sources": [
    {
      "id": "open_meteo",
      "name": "Open-Meteo",
      "type": "weather",
      "status": "healthy",
      "sourceCheckedAt": "2026-07-15T08:30:51.379Z",
      "lastSuccessfulAt": "2026-07-15T08:30:51.379Z",
      "error": null
    },
    {
      "id": "event_feeds",
      "name": "Alert and incident sources",
      "type": "events",
      "status": "healthy",
      "sourceCheckedAt": "2026-07-15T08:30:51.914Z",
      "lastSuccessfulAt": "2026-07-15T08:30:51.914Z",
      "error": null
    },
    {
      "id": "imd_nowcast",
      "name": "IMD Pune Nowcast",
      "status": "healthy",
      "sourceCheckedAt": "2026-07-15T08:30:51.914Z",
      "lastSuccessfulAt": "2026-07-15T08:30:51.914Z",
      "error": null,
      "etag": null,
      "itemsCollected": 0,
      "type": "alerts"
    },
    {
      "id": "ndma_sachet",
      "name": "NDMA SACHET Maharashtra CAP",
      "status": "healthy",
      "sourceCheckedAt": "2026-07-15T08:30:51.914Z",
      "lastSuccessfulAt": "2026-07-15T08:30:51.914Z",
      "error": null,
      "etag": "W/\"8785-1784103629016\"",
      "itemsCollected": 0,
      "type": "alerts"
    },
    {
      "id": "indian_express_pune",
      "name": "Indian Express Pune",
      "status": "healthy",
      "sourceCheckedAt": "2026-07-15T08:30:51.914Z",
      "lastSuccessfulAt": "2026-07-15T08:30:51.914Z",
      "error": null,
      "etag": null,
      "itemsCollected": 0,
      "type": "incidents"
    },
    {
      "id": "hindustan_times_pune",
      "name": "Hindustan Times Pune",
      "status": "healthy",
      "sourceCheckedAt": "2026-07-15T08:30:51.914Z",
      "lastSuccessfulAt": "2026-07-15T08:30:51.914Z",
      "error": null,
      "etag": null,
      "itemsCollected": 0,
      "type": "incidents"
    },
    {
      "id": "pune_metro",
      "name": "Pune Metro Official Updates",
      "status": "healthy",
      "sourceCheckedAt": "2026-07-15T08:30:51.914Z",
      "lastSuccessfulAt": "2026-07-15T08:30:51.914Z",
      "error": null,
      "etag": null,
      "itemsCollected": 0,
      "type": "incidents"
    },
    {
      "id": "free_news_api",
      "name": "FreeNewsAPI trusted-media discovery",
      "status": "unavailable",
      "sourceCheckedAt": "2026-07-15T08:30:51.914Z",
      "lastSuccessfulAt": "2026-07-15T05:59:47.000Z",
      "error": "This operation was aborted",
      "type": "incidents"
    },
    {
      "id": "newsdata_io",
      "name": "NewsData.io trusted-media backup",
      "status": "healthy",
      "sourceCheckedAt": "2026-07-15T08:30:51.914Z",
      "lastSuccessfulAt": "2026-07-15T08:30:51.914Z",
      "error": null,
      "etag": null,
      "itemsCollected": 1,
      "type": "incidents"
    },
    {
      "id": "google_news_discovery",
      "name": "Google News trusted-media discovery",
      "status": "healthy",
      "sourceCheckedAt": "2026-07-15T08:30:51.914Z",
      "lastSuccessfulAt": "2026-07-15T08:30:51.914Z",
      "error": null,
      "itemsCollected": 0,
      "itemsQualified": 0,
      "type": "incidents"
    },
    {
      "id": "maharashtra_rtdas",
      "name": "Maharashtra WRD River & Dam RTDAS",
      "type": "river",
      "status": "current",
      "sourceCheckedAt": "2026-07-15T08:31:12.785Z",
      "lastSuccessfulAt": "2026-07-15T08:31:12.785Z",
      "error": null
    }
  ],
  "generatedAt": "2026-07-15T08:31:14.580Z"
}